ProxNest/__init__.py
ProxNest/logs.py
ProxNest/utils.py
ProxNest/operators/__init__.py
ProxNest/operators/proximal_operators.py
ProxNest/operators/sensing_operators.py
ProxNest/operators/wavelet_operators.py
ProxNest/optimisations/__init__.py
ProxNest/optimisations/l1_norm_prox.py
ProxNest/optimisations/l2_ball_proj.py
ProxNest/optimisations/tv_norm_prox.py
ProxNest/sampling/__init__.py
ProxNest/sampling/proximal_nested.py
ProxNest/sampling/resampling.py
ProxNest-0.0.7.dist-info/LICENSE.txt
ProxNest-0.0.7.dist-info/LICENSE_EXT.txt
ProxNest-0.0.7.dist-info/METADATA
ProxNest-0.0.7.dist-info/WHEEL
ProxNest-0.0.7.dist-info/top_level.txt
ProxNest-0.0.7.dist-info/RECORD
