Metadata-Version: 2.1
Name: ProxNest
Version: 0.0.7
Summary: Proximal nested sampling for high-dimensional Bayesian model selection
Home-page: https://github.com/astro-informatics/proxnest
Author: Xiaohao Cai, Jason McEwen, Marcelo Pereyra, Matthew Price
Author-email: x.cai@soton.ac.uk
License: GNU General Public License v3 (GPLv3)
Platform: UNKNOWN
Classifier: Programming Language :: Python :: 3.6
Classifier: Programming Language :: Python :: 3.7
Classifier: Programming Language :: Python :: 3.8
Classifier: Programming Language :: Python :: 3.9
Classifier: Operating System :: OS Independent
Classifier: Intended Audience :: Developers
Classifier: Intended Audience :: Science/Research
License-File: LICENSE.txt
License-File: LICENSE_EXT.txt
Requires-Dist: numpy
Requires-Dist: colorlog
Requires-Dist: pyyaml
Requires-Dist: PyWavelets
Requires-Dist: tqdm
